zeldarose/__init__.py
zeldarose/common.py
zeldarose/main.py
zeldarose/train_tokenizer.py
zeldarose/train_transformer.py
zeldarose/utils.py
zeldarose/datasets/__init__.py
zeldarose/datasets/mbart.py
zeldarose/datasets/seq2seq.py
zeldarose/datasets/transform.py
zeldarose/tasks/__init__.py
zeldarose/tasks/mbart.py
zeldarose/tasks/mlm.py
zeldarose/tasks/ntp.py
zeldarose/tasks/rtd.py
zeldarose-0.13.0.dist-info/licenses/LICENCE.md
zeldarose-0.13.0.dist-info/METADATA
zeldarose-0.13.0.dist-info/WHEEL
zeldarose-0.13.0.dist-info/entry_points.txt
zeldarose-0.13.0.dist-info/top_level.txt
zeldarose-0.13.0.dist-info/RECORD
