Metadata-Version: 2.4
Name: zeldarose
Version: 0.13.0
Summary: Train transformer-based models
Author-email: Loïc Grobol <loic.grobol@gmail.com>
License: MIT
Project-URL: Bug Tracker, https://github.com/loicgrobol/zeldarose/issues
Project-URL: Changes, https://github.com/loicgrobol/zeldarose/blob/main/CHANGELOG.md
Project-URL: Documentation, https://zeldarose.readthedocs.io
Project-URL: Source Code, https://github.com/loicgrobol/zeldarose
Keywords: nlp,transformers,language-model
Classifier: License :: OSI Approved :: MIT License
Classifier: Programming Language :: Python :: 3.10
Classifier: Programming Language :: Python :: 3.11
Classifier: Programming Language :: Python :: 3.12
Classifier: Programming Language :: Python :: 3.13
Classifier: Environment :: Console
Requires-Python: >=3.10
License-File: LICENCE.md
Requires-Dist: click<9.0,>=8.0.4
Requires-Dist: datasets<4.1,>=3.0
Requires-Dist: filelock
Requires-Dist: jsonlines
Requires-Dist: lightning<2.6,>=2.5.3
Requires-Dist: loguru
Requires-Dist: pydantic
Requires-Dist: pytorch-lightning<2.6,>=2.5.3
Requires-Dist: rich<15,>=14
Requires-Dist: sacrebleu
Requires-Dist: sacremoses
Requires-Dist: system_info
Requires-Dist: tensorboardx
Requires-Dist: torchmetrics<2.0,>=1.0
Requires-Dist: tokenizers<0.22,>=0.10
Requires-Dist: tomli
Requires-Dist: torch<2.9,>=2.0
Requires-Dist: transformers<5.0,>=4.55
Provides-Extra: lint
Requires-Dist: mypy; extra == "lint"
Requires-Dist: ruff; extra == "lint"
Provides-Extra: tests
Requires-Dist: pytest; extra == "tests"
Requires-Dist: pytest-console-scripts; extra == "tests"
Requires-Dist: pytest-github-actions-annotate-failures; extra == "tests"
Dynamic: license-file
